Workbook

Sheet peringkat otomatis
A1: REKAPITULASI NILAI LOMBA KOMPETENSI SISWA (LKS) KOTA SEMARANG
A2: MATA LOMBA AKUNTANSI
A3: SEMARANG, 16-17 MARET 2022
A5: No. Peserta | B5: Nama Peserta | C5: Nama Sekolah | D5: Praktik Akuntansi Manual (45%) | E5: Praktik Komputer Akuntansi (35%) | F5: Presentasi (10%) | G5: Teori Akuntansi (10%) | H5: Jumlah | I5: Nilai Akhir | J5: Peringkat
A6: 3 | B6: Bella Fadila Utami | D6: 90 | E6: ='Komputer Akuntansi'!R7 -> 78.740766 | F6: ='Rekap Nilai Presentasi'!F8 -> 93 | G6: ='Rekap Nilai Teori Akuntansi'!E8 -> 87.5 | H6: =SUM(D6:G6) -> 349.24077 | I6: =(D6*45%)+(E6*35%)+(F6*10%)+(G6*10%) -> 86.109268 | J6: 1
A7: 6 | B7: Alfiana Azzahro Rudianingrum | D7: 84 | E7: ='Komputer Akuntansi'!R10 -> 81.987327 | F7: ='Rekap Nilai Presentasi'!F11 -> 73 | G7: ='Rekap Nilai Teori Akuntansi'!E11 -> 67.5 | H7: =SUM(D7:G7) -> 306.48733 | I7: =(D7*45%)+(E7*35%)+(F7*10%)+(G7*10%) -> 80.545565 | J7: 2
A8: 11 | B8: Luh Sinta Kemalahati | D8: 83.5 | E8: ='Komputer Akuntansi'!R15 -> 79.406699 | F8: ='Rekap Nilai Presentasi'!F16 -> 76.5 | G8: ='Rekap Nilai Teori Akuntansi'!E16 -> 67.5 | H8: =SUM(D8:G8) -> 306.9067 | I8: =(D8*45%)+(E8*35%)+(F8*10%)+(G8*10%) -> 79.767345 | J8: 3
A9: 15 | B9: Michael Christ Kurniawan | D9: 88 | E9: ='Komputer Akuntansi'!R19 -> 61.264104 | F9: ='Rekap Nilai Presentasi'!F20 -> 59 | G9: ='Rekap Nilai Teori Akuntansi'!E20 -> 70 | H9: =SUM(D9:G9) -> 278.2641 | I9: =(D9*45%)+(E9*35%)+(F9*10%)+(G9*10%) -> 73.942436 | J9: 4
A10: 4 | B10: Aullyaa' Putri Ayoe | D10: 80.5 | E10: ='Komputer Akuntansi'!R8 -> 68.591136 | F10: ='Rekap Nilai Presentasi'!F9 -> 69 | G10: ='Rekap Nilai Teori Akuntansi'!E9 -> 67.5 | H10: =SUM(D10:G10) -> 285.59114 | I10: =(D10*45%)+(E10*35%)+(F10*10%)+(G10*10%) -> 73.881898 | J10: 5
A11: 5 | B11: Nabila Putri Abadi | D11: 78 | E11: ='Komputer Akuntansi'!R9 -> 72.522518 | F11: ='Rekap Nilai Presentasi'!E10 -> 60 | G11: ='Rekap Nilai Teori Akuntansi'!E10 -> 55 | H11: =SUM(D11:G11) -> 265.52252 | I11: =(D11*45%)+(E11*35%)+(F11*10%)+(G11*10%) -> 71.982881 | J11: 6
A12: 12 | B12: Annisa Nur Haiizan | D12: 72 | E12: ='Komputer Akuntansi'!R16 -> 51.129364 | F12: ='Rekap Nilai Presentasi'!F17 -> 59.5 | G12: ='Rekap Nilai Teori Akuntansi'!E17 -> 50 | H12: =SUM(D12:G12) -> 232.62936 | I12: =(D12*45%)+(E12*35%)+(F12*10%)+(G12*10%) -> 61.245277 | J12: 7
A13: 10 | B13: Izza Nisa'ul Fikri | D13: 74 | E13: ='Komputer Akuntansi'!R14 -> 48.192239 | F13: ='Rekap Nilai Presentasi'!F15 -> 42.5 | G13: ='Rekap Nilai Teori Akuntansi'!E15 -> 52.5 | H13: =SUM(D13:G13) -> 217.19224 | I13: =(D13*45%)+(E13*35%)+(F13*10%)+(G13*10%) -> 59.667284 | J13: 8
A14: 1 | B14: Nasywa Inas Royanita Syafroni | D14: 73.5 | E14: ='Komputer Akuntansi'!R5 -> 39.248621 | F14: ='Rekap Nilai Presentasi'!E6 -> 46 | G14: ='Rekap Nilai Teori Akuntansi'!E6 -> 60 | H14: =SUM(D14:G14) -> 218.74862 | I14: =(D14*45%)+(E14*35%)+(F14*10%)+(G14*10%) -> 57.412017 | J14: 9
A15: 2 | B15: Anisya Rosyidiana | D15: 66 | E15: ='Komputer Akuntansi'!R6 -> 43.137394 | F15: ='Rekap Nilai Presentasi'!F7 -> 46 | G15: ='Rekap Nilai Teori Akuntansi'!E7 -> 52.5 | H15: =SUM(D15:G15) -> 207.63739 | I15: =(D15*45%)+(E15*35%)+(F15*10%)+(G15*10%) -> 54.648088 | J15: 10
A16: 13 | B16: Waahyuningrum | D16: 70 | E16: ='Komputer Akuntansi'!R17 -> 37.406036 | F16: ='Rekap Nilai Presentasi'!F18 -> 40.5 | G16: ='Rekap Nilai Teori Akuntansi'!E18 -> 55 | H16: =SUM(D16:G16) -> 202.90604 | I16: =(D16*45%)+(E16*35%)+(F16*10%)+(G16*10%) -> 54.142113 | J16: 11
A17: 7 | B17: Nurul Fitri W | D17: 56 | E17: ='Komputer Akuntansi'!R11 -> 49.082094 | F17: ='Rekap Nilai Presentasi'!F12 -> 48.5 | G17: ='Rekap Nilai Teori Akuntansi'!E12 -> 55 | H17: =SUM(D17:G17) -> 208.58209 | I17: =(D17*45%)+(E17*35%)+(F17*10%)+(G17*10%) -> 52.728733 | J17: 12
A18: 14 | B18: Febriana Lisa S | D18: 61 | E18: ='Komputer Akuntansi'!R18 -> 48.537477 | F18: ='Rekap Nilai Presentasi'!F19 -> 33.5 | G18: ='Rekap Nilai Teori Akuntansi'!E19 -> 47.5 | H18: =SUM(D18:G18) -> 190.53748 | I18: =(D18*45%)+(E18*35%)+(F18*10%)+(G18*10%) -> 52.538117 | J18: 13
A19: 9 | B19: Eka Maghrifa | D19: 58 | E19: ='Komputer Akuntansi'!R13 -> 38.988881 | F19: ='Rekap Nilai Presentasi'!F14 -> 32.5 | G19: ='Rekap Nilai Teori Akuntansi'!E14 -> 45 | H19: =SUM(D19:G19) -> 174.48888 | I19: =(D19*45%)+(E19*35%)+(F19*10%)+(G19*10%) -> 47.496108 | J19: 14
A20: 8 | B20: Yunita Fitriani | D20: 54.5 | E20: ='Komputer Akuntansi'!R12 -> 34.170699 | F20: ='Rekap Nilai Presentasi'!F13 -> 36.5 | G20: ='Rekap Nilai Teori Akuntansi'!E13 -> 20 | H20: =SUM(D20:G20) -> 145.1707 | I20: =(D20*45%)+(E20*35%)+(F20*10%)+(G20*10%) -> 42.134745 | J20: 15
G23: Semarang, 17 Maret 2022
C25: Juri 1 | G25: Juri
C30: Utik Titiastri, SE. Akt. CA.CPA. | G30: Kardiyem, S.Pd., M.Pd., CAAT., CADE., CQnR.,CRMP

Sheet peringkat
A1: REKAPITULASI NILAI LOMBA KOMPETENSI SISWA (LKS) KOTA SEMARANG
A2: MATA LOMBA AKUNTANSI
A3: SEMARANG, 16-17 MARET 2022
A5: No. Peserta | B5: Nama Peserta | C5: Nama Sekolah | D5: Praktik Akuntansi Manual (45%) | E5: Praktik Komputer Akuntansi (35%) | F5: Presentasi (10%) | G5: Teori Akuntansi (10%) | H5: Jumlah | I5: Nilai Akhir | J5: Peringkat
A6: 1 | B6: Nasywa Inas Royanita Syafroni | D6: 73.5 | E6: ='Komputer Akuntansi'!R5 -> 39.248621 | F6: ='Rekap Nilai Presentasi'!E6 -> 46 | G6: ='Rekap Nilai Teori Akuntansi'!E6 -> 60 | H6: =SUM(D6:G6) -> 218.74862 | I6: =(D6*45%)+(E6*35%)+(F6*10%)+(G6*10%) -> 57.412017
A7: 2 | B7: Anisya Rosyidiana | D7: 66 | E7: ='Komputer Akuntansi'!R6 -> 43.137394 | F7: ='Rekap Nilai Presentasi'!F7 -> 46 | G7: ='Rekap Nilai Teori Akuntansi'!E7 -> 52.5 | H7: =SUM(D7:G7) -> 207.63739 | I7: =(D7*45%)+(E7*35%)+(F7*10%)+(G7*10%) -> 54.648088
A8: 3 | B8: Bella Fadila Utami | D8: 90 | E8: ='Komputer Akuntansi'!R7 -> 78.740766 | F8: ='Rekap Nilai Presentasi'!F8 -> 93 | G8: ='Rekap Nilai Teori Akuntansi'!E8 -> 87.5 | H8: =SUM(D8:G8) -> 349.24077 | I8: =(D8*45%)+(E8*35%)+(F8*10%)+(G8*10%) -> 86.109268 | J8: 1
A9: 4 | B9: Aullyaa' Putri Ayoe | D9: 80.5 | E9: ='Komputer Akuntansi'!R8 -> 68.591136 | F9: ='Rekap Nilai Presentasi'!F9 -> 69 | G9: ='Rekap Nilai Teori Akuntansi'!E9 -> 67.5 | H9: =SUM(D9:G9) -> 285.59114 | I9: =(D9*45%)+(E9*35%)+(F9*10%)+(G9*10%) -> 73.881898 | J9: 5
A10: 5 | B10: Nabila Putri Abadi | D10: 78 | E10: ='Komputer Akuntansi'!R9 -> 72.522518 | F10: ='Rekap Nilai Presentasi'!E10 -> 60 | G10: ='Rekap Nilai Teori Akuntansi'!E10 -> 55 | H10: =SUM(D10:G10) -> 265.52252 | I10: =(D10*45%)+(E10*35%)+(F10*10%)+(G10*10%) -> 71.982881 | J10: 6
A11: 6 | B11: Alfiana Azzahro Rudianingrum | D11: 84 | E11: ='Komputer Akuntansi'!R10 -> 81.987327 | F11: ='Rekap Nilai Presentasi'!F11 -> 73 | G11: ='Rekap Nilai Teori Akuntansi'!E11 -> 67.5 | H11: =SUM(D11:G11) -> 306.48733 | I11: =(D11*45%)+(E11*35%)+(F11*10%)+(G11*10%) -> 80.545565 | J11: 2
A12: 7 | B12: Nurul Fitri W | D12: 56 | E12: ='Komputer Akuntansi'!R11 -> 49.082094 | F12: ='Rekap Nilai Presentasi'!F12 -> 48.5 | G12: ='Rekap Nilai Teori Akuntansi'!E12 -> 55 | H12: =SUM(D12:G12) -> 208.58209 | I12: =(D12*45%)+(E12*35%)+(F12*10%)+(G12*10%) -> 52.728733
A13: 8 | B13: Yunita Fitriani | D13: 54.5 | E13: ='Komputer Akuntansi'!R12 -> 34.170699 | F13: ='Rekap Nilai Presentasi'!F13 -> 36.5 | G13: ='Rekap Nilai Teori Akuntansi'!E13 -> 20 | H13: =SUM(D13:G13) -> 145.1707 | I13: =(D13*45%)+(E13*35%)+(F13*10%)+(G13*10%) -> 42.134745
A14: 9 | B14: Eka Maghrifa | D14: 58 | E14: ='Komputer Akuntansi'!R13 -> 38.988881 | F14: ='Rekap Nilai Presentasi'!F14 -> 32.5 | G14: ='Rekap Nilai Teori Akuntansi'!E14 -> 45 | H14: =SUM(D14:G14) -> 174.48888 | I14: =(D14*45%)+(E14*35%)+(F14*10%)+(G14*10%) -> 47.496108
A15: 10 | B15: Izza Nisa'ul Fikri | D15: 74 | E15: ='Komputer Akuntansi'!R14 -> 48.192239 | F15: ='Rekap Nilai Presentasi'!F15 -> 42.5 | G15: ='Rekap Nilai Teori Akuntansi'!E15 -> 52.5 | H15: =SUM(D15:G15) -> 217.19224 | I15: =(D15*45%)+(E15*35%)+(F15*10%)+(G15*10%) -> 59.667284
A16: 11 | B16: Luh Sinta Kemalahati | D16: 83.5 | E16: ='Komputer Akuntansi'!R15 -> 79.406699 | F16: ='Rekap Nilai Presentasi'!F16 -> 76.5 | G16: ='Rekap Nilai Teori Akuntansi'!E16 -> 67.5 | H16: =SUM(D16:G16) -> 306.9067 | I16: =(D16*45%)+(E16*35%)+(F16*10%)+(G16*10%) -> 79.767345 | J16: 3
A17: 12 | B17: Annisa Nur Haiizan | D17: 72 | E17: ='Komputer Akuntansi'!R16 -> 51.129364 | F17: ='Rekap Nilai Presentasi'!F17 -> 59.5 | G17: ='Rekap Nilai Teori Akuntansi'!E17 -> 50 | H17: =SUM(D17:G17) -> 232.62936 | I17: =(D17*45%)+(E17*35%)+(F17*10%)+(G17*10%) -> 61.245277
A18: 13 | B18: Waahyuningrum | D18: 70 | E18: ='Komputer Akuntansi'!R17 -> 37.406036 | F18: ='Rekap Nilai Presentasi'!F18 -> 40.5 | G18: ='Rekap Nilai Teori Akuntansi'!E18 -> 55 | H18: =SUM(D18:G18) -> 202.90604 | I18: =(D18*45%)+(E18*35%)+(F18*10%)+(G18*10%) -> 54.142113
A19: 14 | B19: Febriana Lisa S | D19: 61 | E19: ='Komputer Akuntansi'!R18 -> 48.537477 | F19: ='Rekap Nilai Presentasi'!F19 -> 33.5 | G19: ='Rekap Nilai Teori Akuntansi'!E19 -> 47.5 | H19: =SUM(D19:G19) -> 190.53748 | I19: =(D19*45%)+(E19*35%)+(F19*10%)+(G19*10%) -> 52.538117
A20: 15 | B20: Michael Christ Kurniawan | D20: 88 | E20: ='Komputer Akuntansi'!R19 -> 61.264104 | F20: ='Rekap Nilai Presentasi'!F20 -> 59 | G20: ='Rekap Nilai Teori Akuntansi'!E20 -> 70 | H20: =SUM(D20:G20) -> 278.2641 | I20: =(D20*45%)+(E20*35%)+(F20*10%)+(G20*10%) -> 73.942436 | J20: 4
G23: Semarang, 17 Maret 2022
C25: Juri 1 | G25: Juri 2
C30: Utik Titiastri, SE. Akt. CA.CPA. | G30: Kardiyem, S.Pd., M.Pd., CAAT., CADE., CQnR.

Sheet Form penilaian presentasi
A1: FORM PENILAIAN MATA UJI PRESENTASI BAHASA INGGRIS
A2: LOMBA KETERAMPILAN SISWA (LKS) TINGKAT KOTA SEMARANG
A3: MATA LOMBA AKUNTANSI
A4: SEMARANG, 16-17 MARET 2022
A6: NAMA | B6: :
A7: NOMOR | B7: :
A9: NO. | B9: ITEM PENILAIAN | C9: RENTANG SKOR | D9: SKOR
A10: 1 | B10: Grammar | C10: 5-10
A11: 2 | B11: Accuracy | C11: 5-25
A12: 3 | B12: Fluency | C12: 5-20
A13: 4 | B13: Pronounciation | C13: 5-15
A14: 5 | B14: Overall Performance | C14: 5-30
B15: TOTAL | C15: 100
C18: Semarang, 17 Maret 2022
B19: Dewan Juri | C19: Dewan Juri

Sheet REKAPITULASI SEMUA MATA LOMBA
A1: REKAPITULASI NILAI LOMBA KOMPETENSI SISWA (LKS) KOTA SEMARANG
A2: MATA LOMBA AKUNTANSI
A3: SEMARANG, 16-17 MARET 2022
A5: No. Peserta | B5: Nama Peserta | C5: Nama Sekolah | D5: Praktik Akuntansi Manual (45%) | E5: Praktik Komputer Akuntansi (35%) | F5: Presentasi (10%) | G5: Teori Akuntansi (10%) | H5: Jumlah | I5: Nilai Akhir | J5: Peringkat
A6: 1 | B6: Nasywa Inas Royanita Syafroni | D6: 73.5 | E6: ='Komputer Akuntansi'!R5 -> 39.248621 | F6: ='Rekap Nilai Presentasi'!E6 -> 46 | G6: ='Rekap Nilai Teori Akuntansi'!E6 -> 60 | H6: =SUM(D6:G6) -> 218.74862 | I6: =(D6*45%)+(E6*35%)+(F6*10%)+(G6*10%) -> 57.412017
A7: 2 | B7: Anisya Rosyidiana | D7: 66 | E7: ='Komputer Akuntansi'!R6 -> 43.137394 | F7: ='Rekap Nilai Presentasi'!F7 -> 46 | G7: ='Rekap Nilai Teori Akuntansi'!E7 -> 52.5 | H7: =SUM(D7:G7) -> 207.63739 | I7: =(D7*45%)+(E7*35%)+(F7*10%)+(G7*10%) -> 54.648088
A8: 3 | B8: Bella Fadila Utami | D8: 90 | E8: ='Komputer Akuntansi'!R7 -> 78.740766 | F8: ='Rekap Nilai Presentasi'!F8 -> 93 | G8: ='Rekap Nilai Teori Akuntansi'!E8 -> 87.5 | H8: =SUM(D8:G8) -> 349.24077 | I8: =(D8*45%)+(E8*35%)+(F8*10%)+(G8*10%) -> 86.109268
A9: 4 | B9: Aullyaa' Putri Ayoe | D9: 80.5 | E9: ='Komputer Akuntansi'!R8 -> 68.591136 | F9: ='Rekap Nilai Presentasi'!F9 -> 69 | G9: ='Rekap Nilai Teori Akuntansi'!E9 -> 67.5 | H9: =SUM(D9:G9) -> 285.59114 | I9: =(D9*45%)+(E9*35%)+(F9*10%)+(G9*10%) -> 73.881898
A10: 5 | B10: Nabila Putri Abadi | D10: 78 | E10: ='Komputer Akuntansi'!R9 -> 72.522518 | F10: ='Rekap Nilai Presentasi'!E10 -> 60 | G10: ='Rekap Nilai Teori Akuntansi'!E10 -> 55 | H10: =SUM(D10:G10) -> 265.52252 | I10: =(D10*45%)+(E10*35%)+(F10*10%)+(G10*10%) -> 71.982881
A11: 6 | B11: Alfiana Azzahro Rudianingrum | D11: 84 | E11: ='Komputer Akuntansi'!R10 -> 81.987327 | F11: ='Rekap Nilai Presentasi'!F11 -> 73 | G11: ='Rekap Nilai Teori Akuntansi'!E11 -> 67.5 | H11: =SUM(D11:G11) -> 306.48733 | I11: =(D11*45%)+(E11*35%)+(F11*10%)+(G11*10%) -> 80.545565
A12: 7 | B12: Nurul Fitri W | D12: 56 | E12: ='Komputer Akuntansi'!R11 -> 49.082094 | F12: ='Rekap Nilai Presentasi'!F12 -> 48.5 | G12: ='Rekap Nilai Teori Akuntansi'!E12 -> 55 | H12: =SUM(D12:G12) -> 208.58209 | I12: =(D12*45%)+(E12*35%)+(F12*10%)+(G12*10%) -> 52.728733
A13: 8 | B13: Yunita Fitriani | D13: 54.5 | E13: ='Komputer Akuntansi'!R12 -> 34.170699 | F13: ='Rekap Nilai Presentasi'!F13 -> 36.5 | G13: ='Rekap Nilai Teori Akuntansi'!E13 -> 20 | H13: =SUM(D13:G13) -> 145.1707 | I13: =(D13*45%)+(E13*35%)+(F13*10%)+(G13*10%) -> 42.134745
A14: 9 | B14: Eka Maghrifa | D14: 58 | E14: ='Komputer Akuntansi'!R13 -> 38.988881 | F14: ='Rekap Nilai Presentasi'!F14 -> 32.5 | G14: ='Rekap Nilai Teori Akuntansi'!E14 -> 45 | H14: =SUM(D14:G14) -> 174.48888 | I14: =(D14*45%)+(E14*35%)+(F14*10%)+(G14*10%) -> 47.496108
A15: 10 | B15: Izza Nisa'ul Fikri | D15: 74 | E15: ='Komputer Akuntansi'!R14 -> 48.192239 | F15: ='Rekap Nilai Presentasi'!F15 -> 42.5 | G15: ='Rekap Nilai Teori Akuntansi'!E15 -> 52.5 | H15: =SUM(D15:G15) -> 217.19224 | I15: =(D15*45%)+(E15*35%)+(F15*10%)+(G15*10%) -> 59.667284
A16: 11 | B16: Luh Sinta Kemalahati | D16: 83.5 | E16: ='Komputer Akuntansi'!R15 -> 79.406699 | F16: ='Rekap Nilai Presentasi'!F16 -> 76.5 | G16: ='Rekap Nilai Teori Akuntansi'!E16 -> 67.5 | H16: =SUM(D16:G16) -> 306.9067 | I16: =(D16*45%)+(E16*35%)+(F16*10%)+(G16*10%) -> 79.767345
A17: 12 | B17: Annisa Nur Haiizan | D17: 72 | E17: ='Komputer Akuntansi'!R16 -> 51.129364 | F17: ='Rekap Nilai Presentasi'!F17 -> 59.5 | G17: ='Rekap Nilai Teori Akuntansi'!E17 -> 50 | H17: =SUM(D17:G17) -> 232.62936 | I17: =(D17*45%)+(E17*35%)+(F17*10%)+(G17*10%) -> 61.245277
A18: 13 | B18: Waahyuningrum | D18: 70 | E18: ='Komputer Akuntansi'!R17 -> 37.406036 | F18: ='Rekap Nilai Presentasi'!F18 -> 40.5 | G18: ='Rekap Nilai Teori Akuntansi'!E18 -> 55 | H18: =SUM(D18:G18) -> 202.90604 | I18: =(D18*45%)+(E18*35%)+(F18*10%)+(G18*10%) -> 54.142113
A19: 14 | B19: Febriana Lisa S | D19: 61 | E19: ='Komputer Akuntansi'!R18 -> 48.537477 | F19: ='Rekap Nilai Presentasi'!F19 -> 33.5 | G19: ='Rekap Nilai Teori Akuntansi'!E19 -> 47.5 | H19: =SUM(D19:G19) -> 190.53748 | I19: =(D19*45%)+(E19*35%)+(F19*10%)+(G19*10%) -> 52.538117
A20: 15 | B20: Michael Christ Kurniawan | D20: 88 | E20: ='Komputer Akuntansi'!R19 -> 61.264104 | F20: ='Rekap Nilai Presentasi'!F20 -> 59 | G20: ='Rekap Nilai Teori Akuntansi'!E20 -> 70 | H20: =SUM(D20:G20) -> 278.2641 | I20: =(D20*45%)+(E20*35%)+(F20*10%)+(G20*10%) -> 73.942436
G23: Semarang, 17 Maret 2022
C25: Juri 1 | G25: Juri 2
C30: Utik Titiastri, SE. Akt. CA.CPA. | G30: Kardiyem, S.Pd., M.Pd., CAAT., CADE., CQnR.

Sheet Rekap Nilai Teori Akuntansi
A1: REKAPITULASI NILAI PRESENTASI LKS KOTA SEMARANG
A2: MATA LOMBA AKUNTANSI
A3: SEMARANG, 16-17 MARET 2022
A5: No. | B5: Nama Peserta | C5: Nama Sekolah | D5: Jumlah Benar | E5: Benar X Skor
A6: 1 | B6: Nasywa Inas Royanita Syafroni | D6: 24 | E6: =D6*2.5 -> 60
A7: 2 | B7: Anisya Rosyidiana | D7: 21 | E7: =D7*2.5 -> 52.5
A8: 3 | B8: Bella Fadila Utami | D8: 35 | E8: =D8*2.5 -> 87.5
A9: 4 | B9: Aullyaa' Putri Ayoe | D9: 27 | E9: =D9*2.5 -> 67.5
A10: 5 | B10: Nabila Putri Abadi | D10: 22 | E10: =D10*2.5 -> 55
A11: 6 | B11: Alfiana Azzahro Rudianingrum | D11: 27 | E11: =D11*2.5 -> 67.5
A12: 7 | B12: Nurul Fitri W | D12: 22 | E12: =D12*2.5 -> 55
A13: 8 | B13: Yunita Fitriani | D13: 8 | E13: =D13*2.5 -> 20
A14: 9 | B14: Eka Maghrifa | D14: 18 | E14: =D14*2.5 -> 45
A15: 10 | B15: Izza Nisa'ul Fikri | D15: 21 | E15: =D15*2.5 -> 52.5
A16: 11 | B16: Luh Sinta Kemalahati | D16: 27 | E16: =D16*2.5 -> 67.5
A17: 12 | B17: Annisa Nur Haiizan | D17: 20 | E17: =D17*2.5 -> 50
... A20: 15 | B20: Michael Christ Kurniawan | D20: 28 | E20: =D20*2.5 -> 70
D22: Semarang, 17 Maret 2022
A23: Juri 1 | D23: Juri 2
D27: Kardiyem, S.Pd., M.Pd., CAAT., CADE., CQnR.

Sheet Rekap Nilai Presentasi
A1: REKAPITULASI NILAI PRESENTASI LKS KOTA SEMARANG
A2: MATA LOMBA AKUNTANSI
A3: SEMARANG, 16-17 MARET 2022
A5: No. | B5: Nama Peserta | C5: Nama Sekolah | D5: Nilai Juri 1 | E5: Nilai Juri 2 | F5: Nilai Akhir
A6: 1 | B6: Nasywa Inas Royanita Syafroni | D6: 62 | E6: 46 | F6: =AVERAGE(D6:E6) -> 54
A7: 2 | B7: Anisya Rosyidiana | D7: 49 | E7: 43 | F7: =AVERAGE(D7:E7) -> 46
A8: 3 | B8: Bella Fadila Utami | D8: 94 | E8: 92 | F8: =AVERAGE(D8:E8) -> 93
A9: 4 | B9: Aullyaa' Putri Ayoe | D9: 68 | E9: 70 | F9: =AVERAGE(D9:E9) -> 69
A10: 5 | B10: Nabila Putri Abadi | D10: 65 | E10: 60 | F10: =AVERAGE(D10:E10) -> 62.5
A11: 6 | B11: Alfiana Azzahro Rudianingrum | D11: 77 | E11: 69 | F11: =AVERAGE(D11:E11) -> 73
A12: 7 | B12: Nurul Fitri W | D12: 52 | E12: 45 | F12: =AVERAGE(D12:E12) -> 48.5
A13: 8 | B13: Yunita Fitriani | D13: 34 | E13: 39 | F13: =AVERAGE(D13:E13) -> 36.5
A14: 9 | B14: Eka Maghrifa | D14: 25 | E14: 40 | F14: =AVERAGE(D14:E14) -> 32.5
A15: 10 | B15: Izza Nisa'ul Fikri | D15: 45 | E15: 40 | F15: =AVERAGE(D15:E15) -> 42.5
A16: 11 | B16: Luh Sinta Kemalahati | D16: 73 | E16: 80 | F16: =AVERAGE(D16:E16) -> 76.5
A17: 12 | B17: Annisa Nur Haiizan | D17: 57 | E17: 62 | F17: =AVERAGE(D17:E17) -> 59.5
... A20: 15 | B20: Michael Christ Kurniawan | D20: 60 | E20: 58 | F20: =AVERAGE(D20:E20) -> 59
D22: Semarang, 17 Maret 2022
A23: Juri 1 | D23: Juri 2
D27: Kardiyem, S.Pd., M.Pd., CAAT., CADE., CQnR.

Sheet Komputer Akuntansi
A1: No. Peserta | B1: Nama Peserta | H1: 11 | I1: 14 | J1: 10 | K1: 22 | L1: 8 | M1: 8 | N1: 31 | O1: 32 | P1: 42
C2: data bisnis | D2: daftar akun | E2: data pelanggan | F2: data supplier | G2: persediaan | H2: J. Kas Masuk | I2: J. Kas Keluar | J2: J. Pemb | K2: J. Penj | L2: J. Umum | M2: J. Penyesuaian | N2: L/R | O2: LAK | P2: Neraca | Q2: Sikap | R2: Total
H3: =H4/H1 -> 0.90909091 | I3: =I4/I1 -> 0.71428571 | J3: =J4/J1 -> 1 | K3: =K4/K1 -> 0.45454545 | L3: =L4/L1 -> 0.875 | M3: =M4/M1 -> 1 | N3: =N4/N1 -> 0.12903226 | O3: =O4/O1 -> 0.125 | P3: =P4/P1 -> 0.095238095 | Q3: 10
C4: 4 | D4: 4 | E4: 5 | F4: 5 | G4: 5 | H4: 10 | I4: 10 | J4: 10 | K4: 10 | L4: 7 | M4: 8 | N4: 4 | O4: 4 | P4: 4 | Q4: 10 | R4: =SUM(C4:Q4) -> 100
A5: 1 | B5: Nasywa Inas Royanita Syafroni | C5: 4 | D5: 4 | E5: 5 | F5: 5 | G5: 5 | H5: 0 | I5: 1 | J5: 3 | K5: 3 | L5: 0 | M5: 0 | N5: 1 | O5: 3 | P5: 7 | Q5: 10 | R5: =(C5+D5+E5+F5+G5+(H5*H$3)+(I5*I$3)+(J5*J$3)+(K5*K$3)+(L5*L$3)+(M5*M$3)+(N5*N$3)+(O5*O$3)+(P5*P$3)+Q5) -> 39.248621
A6: 2 | B6: Anisya Rosyidiana | C6: 4 | D6: 4 | E6: 5 | F6: 5 | G6: 5 | H6: 1 | I6: 10 | J6: 0 | K6: 0 | L6: 0 | M6: 0 | N6: 2 | O6: 7 | P6: 10 | Q6: 10 | R6: =(C6+D6+E6+F6+G6+(H6*H$3)+(I6*I$3)+(J6*J$3)+(K6*K$3)+(L6*L$3)+(M6*M$3)+(N6*N$3)+(O6*O$3)+(P6*P$3)+Q6) -> 43.137394
A7: 3 | B7: Bella Fadila Utami | C7: 4 | D7: 4 | E7: 5 | F7: 5 | G7: 5 | H7: 8 | I7: 13 | J7: 8 | K7: 13 | L7: 4 | M7: 5 | N7: 22 | O7: 17 | P7: 19 | Q7: 10 | R7: =(C7+D7+E7+F7+G7+(H7*H$3)+(I7*I$3)+(J7*J$3)+(K7*K$3)+(L7*L$3)+(M7*M$3)+(N7*N$3)+(O7*O$3)+(P7*P$3)+Q7) -> 78.740766
A8: 4 | B8: Aullyaa' Putri Ayoe | C8: 4 | D8: 4 | E8: 5 | F8: 5 | G8: 5 | H8: 5 | I8: 10 | J8: 9 | K8: 7 | L8: 4 | M8: 4 | N8: 12 | O8: 13 | P8: 11 | Q8: 10 | R8: =(C8+D8+E8+F8+G8+(H8*H$3)+(I8*I$3)+(J8*J$3)+(K8*K$3)+(L8*L$3)+(M8*M$3)+(N8*N$3)+(O8*O$3)+(P8*P$3)+Q8) -> 68.591136
A9: 5 | B9: Nabila Putri Abadi | C9: 4 | D9: 4 | E9: 5 | F9: 5 | G9: 5 | H9: 4 | I9: 10 | J9: 9 | K9: 15 | L9: 5 | M9: 5 | N9: 8 | O9: 11 | P9: 12 | Q9: 10 | R9: =(C9+D9+E9+F9+G9+(H9*H$3)+(I9*I$3)+(J9*J$3)+(K9*K$3)+(L9*L$3)+(M9*M$3)+(N9*N$3)+(O9*O$3)+(P9*P$3)+Q9) -> 72.522518
A10: 6 | B10: Alfiana Azzahro Rudianingrum | C10: 4 | D10: 4 | E10: 5 | F10: 5 | G10: 5 | H10: 9 | I10: 13 | J10: 9 | K10: 15 | L10: 5 | M10: 5 | N10: 19 | O10: 15 | P10: 21 | Q10: 10 | R10: =(C10+D10+E10+F10+G10+(H10*H$3)+(I10*I$3)+(J10*J$3)+(K10*K$3)+(L10*L$3)+(M10*M$3)+(N10*N$3)+(O10*O$3)+(P10*P$3)+Q10) -> 81.987327
A11: 7 | B11: Nurul Fitri W | C11: 4 | D11: 4 | E11: 5 | F11: 5 | G11: 5 | H11: 4 | I11: 5 | J11: 4 | K11: 5 | L11: 0 | M11: 0 | N11: 6 | O11: 7 | P11: 10 | Q11: 10 | R11: =(C11+D11+E11+F11+G11+(H11*H$3)+(I11*I$3)+(J11*J$3)+(K11*K$3)+(L11*L$3)+(M11*M$3)+(N11*N$3)+(O11*O$3)+(P11*P$3)+Q11) -> 49.082094
A12: 8 | B12: Yunita Fitriani | C12: 4 | D12: 4 | E12: 5 | F12: 5 | G12: 5 | H12: 0 | I12: 0 | J12: 0 | K12: 0 | L12: 0 | M12: 0 | N12: 1 | O12: 3 | P12: 7 | Q12: 10 | R12: =(C12+D12+E12+F12+G12+(H12*H$3)+(I12*I$3)+(J12*J$3)+(K12*K$3)+(L12*L$3)+(M12*M$3)+(N12*N$3)+(O12*O$3)+(P12*P$3)+Q12) -> 34.170699
A13: 9 | B13: Eka Maghrifa | C13: 4 | D13: 4 | E13: 5 | F13: 5 | G13: 5 | H13: 0 | I13: 0 | J13: 3 | K13: 4 | L13: 0 | M13: 0 | N13: 1 | O13: 3 | P13: 7 | Q13: 10 | R13: =(C13+D13+E13+F13+G13+(H13*H$3)+(I13*I$3)+(J13*J$3)+(K13*K$3)+(L13*L$3)+(M13*M$3)+(N13*N$3)+(O13*O$3)+(P13*P$3)+Q13) -> 38.988881
A14: 10 | B14: Izza Nisa'ul Fikri | C14: 4 | D14: 4 | E14: 5 | F14: 5 | G14: 5 | H14: 2 | I14: 9 | J14: 3 | K14: 4 | L14: 0 | M14: 0 | N14: 5 | O14: 5 | P14: 9 | Q14: 10 | R14: =(C14+D14+E14+F14+G14+(H14*H$3)+(I14*I$3)+(J14*J$3)+(K14*K$3)+(L14*L$3)+(M14*M$3)+(N14*N$3)+(O14*O$3)+(P14*P$3)+Q14) -> 48.192239
A15: 11 | B15: Luh Sinta Kemalahati | C15: 4 | D15: 4 | E15: 5 | F15: 5 | G15: 5 | H15: 6 | I15: 11 | J15: 8 | K15: 14 | L15: 6 | M15: 7 | N15: 19 | O15: 17 | P15: 20 | Q15: 10 | R15: =(C15+D15+E15+F15+G15+(H15*H$3)+(I15*I$3)+(J15*J$3)+(K15*K$3)+(L15*L$3)+(M15*M$3)+(N15*N$3)+(O15*O$3)+(P15*P$3)+Q15) -> 79.406699
A16: 12 | B16: Annisa Nur Haiizan | C16: 4 | D16: 4 | E16: 5 | F16: 5 | G16: 5 | H16: 3 | I16: 9 | J16: 3 | K16: 4 | L16: 0 | M16: 0 | N16: 9 | O16: 11 | P16: 17 | Q16: 10 | R16: =(C16+D16+E16+F16+G16+(H16*H$3)+(I16*I$3)+(J16*J$3)+(K16*K$3)+(L16*L$3)+(M16*M$3)+(N16*N$3)+(O16*O$3)+(P16*P$3)+Q16) -> 51.129364
... A19: 15 | B19: Michael Christ Kurniawan | C19: 4 | D19: 4 | E19: 5 | F19: 5 | G19: 5 | H19: 5 | I19: 10 | J19: 6 | K19: 10 | L19: 1 | M19: 1 | N19: 9 | O19: 11 | P19: 17 | Q19: 10 | R19: =(C19+D19+E19+F19+G19+(H19*H$3)+(I19*I$3)+(J19*J$3)+(K19*K$3)+(L19*L$3)+(M19*M$3)+(N19*N$3)+(O19*O$3)+(P19*P$3)+Q19) -> 61.264104
H20: 11 | I20: 14 | J20: 10 | K20: 22 | L20: 8 | N20: 32 | O20: 32 | P20: 42

Sheet REKAP-DETAIL
A1: REKAPITULASI NILAI LOMBA KETERAMPILAN SISWA (LKS) TINGKAT JAWA TENGAH
A2: MATA LOMBA AKUNTANSI
A3: SURAKARTA, 14-16 SEPTEMBER 2016
A5: No. | B5: Nama Peserta | C5: Nama Sekolah | D5: Skor Teori Akuntansi | E5: Skor Praktik Akuntansi Manual SESI 1 | O5: Skor Praktik Akuntansi Manual SESI 2 | X5: Skor Praktek Akuntansi Manual SESI 3 | AI5: Skor Aplikasi Komputer Akuntansi | AW5: Presentasi | AX5: Nilai Akhir Total | AY5: Nilai Akhir Total Konversi
E6: Jurnal Pembelian | F6: Jurnal Penjualan | G6: Pengeluaran kas | H6: Penerimaan Kas | I6: Jurnal Umum | J6: Kartu Persediaan | K6: BBP Piutang | L6: BBP Utang | M6: Sikap | N6: entri jurnal | O6: Rekap Jurnal Pembelian | P6: Rekap Jurnal Penjualan | Q6: Rekap Pengeluaran kas | R6: Rekap Penerimaan Kas | S6: Rekap Jurnal Umum | T6: Posting | U6: Neraca Saldo | V6: Sikap | W6: buku besar | X6: Penyesuaian | Y6: Kertas kerja | Z6: Neraca | AA6: Laba Rugi | AB6: Laba Ditahan | AC6: Arus Kas | AD6: jurnal penutup | AE6: NS penutupan | AF6: sikap | AG6: laporan keuangan | AH6: Sub Total | AI6: FILE & AKUN | AJ6: DAFTAR AKUN | AK6: CUST | AL6: SUPP | AM6: INVENTORY | AN6: CASH RECEIPT | AO6: CASH PAYMENT | AP6: SALES | AQ6: PEMBELIAN | AR6: JURNAL UMUM | AS6: L/K | AT6: KECEPATAN | AU6: KETEPATAN | AV6: Sub Total
D7: 0.1 | N7: 0.4 | W7: 0.2 | AG7: 0.4 | AH7: =(N7+W7+AG7)/2 -> 0.5 | AV7: 0.3 | AW7: 0.1 | AX7: =D7+AH7+AV7+AW7 -> 1 | AY7: 1
D8: 100 | E8: 3 | F8: 4 | G8: 8 | H8: 7.5 | I8: 5 | J8: 4 | K8: 2 | L8: 1.5 | M8: 5 | N8: =SUM(E8:M8) -> 40 | O8: 2 | P8: 2 | Q8: 2 | R8: 2 | S8: 2 | T8: 6 | U8: 2 | V8: 2 | W8: =SUM(O8:V8) -> 20 | X8: 6 | Y8: 7 | Z8: 5 | AA8: 5 | AB8: 2 | AC8: 2 | AD8: 5 | AE8: 5 | AF8: 3 | AG8: =SUM(X8:AF8) -> 40 | AH8: =N8+W8+AG8 -> 100 | AI8: 5 | AJ8: 5 | AK8: 5 | AL8: 5 | AM8: 5 | AN8: 10 | AO8: 10 | AP8: 10 | AQ8: 10 | AR8: 7 | AS8: 8 | AT8: 5 | AU8: 5 | AV8: =SUM(AI8:AU8) -> 90 | AW8: 100 | AX8: =D8+AH8+AV8+AW8 -> 390 | AY8: =(10%*D8)+(50%*AH8)+(30%*AV8)+(10%*AW8) -> 97
A9: 1 | D9: =31*2 -> 62 | E9: 2 | F9: 1 | G9: 3.5 | H9: 3 | I9: 2 | J9: 2.7 | K9: 1.3 | L9: 0.4 | M9: 5 | N9: =SUM(E9:M9) -> 20.9 | O9: 2 | P9: 2 | Q9: 2 | R9: 2 | S9: 1.87 | T9: 4.32 | U9: 0.25 | V9: 2 | W9: =SUM(O9:V9) -> 16.44 | X9: 4 | Y9: 5.93 | Z9: 3.375 | AA9: 3.78 | AB9: 1 | AC9: 0 | AD9: 4.17 | AE9: 4.024 | AF9: 2.75 | AG9: =SUM(X9:AF9) -> 29.029 | AH9: =N9+W9+AG9 -> 66.369 | AI9: 5 | AJ9: 5 | AK9: 5 | AL9: 5 | AM9: 5 | AN9: 10 | AO9: 9.46 | AP9: 10 | AQ9: 10 | AR9: 7.5 | AS9: 5.7001183 | AT9: 3 | AU9: 2 | AV9: =SUM(AI9:AU9) -> 82.660118 | AW9: 80 | AX9: =D9+AH9+AV9+AW9 -> 291.02912 | AY9: =(10%*D9)+(50%*AH9)+(30%*AV9)+(10%*AW9) -> 72.182536
A10: 2 | D10: =33*2 -> 66 | E10: 2 | F10: 1 | G10: 1.5 | H10: 1 | I10: 0.5 | J10: 1.6 | K10: 1.6 | L10: 1.4 | M10: 5 | N10: =SUM(E10:M10) -> 15.6 | O10: 2 | P10: 1.78 | Q10: 1.12 | R10: 1.87 | S10: 1.87 | T10: 4.32 | U10: 1.7 | V10: 2 | W10: =SUM(O10:V10) -> 16.66 | X10: 4.5 | Y10: 6.03 | Z10: 3.5 | AA10: 3.29 | AB10: 1 | AC10: 0.7 | AD10: 4 | AE10: 3.41 | AF10: 3 | AG10: =SUM(X10:AF10) -> 29.43 | AH10: =N10+W10+AG10 -> 61.69 | AI10: 5 | AJ10: 5 | AK10: 5 | AL10: 5 | AM10: 5 | AN10: 10 | AO10: 8.2608696 | AP10: 10 | AQ10: 10 | AR10: 0.5 | AS10: 7.0227331 | AT10: 3 | AU10: 2 | AV10: =SUM(AI10:AU10) -> 75.783603 | AW10: 80 | AX10: =D10+AH10+AV10+AW10 -> 283.4736 | AY10: =(10%*D10)+(50%*AH10)+(30%*AV10)+(10%*AW10) -> 68.180081
A11: 3 | D11: =35*2 -> 70 | E11: 2 | F11: 1 | G11: 2.5 | H11: 1 | I11: 3.5 | J11: 1.8 | K11: 1.8 | L11: 1.4 | M11: 5 | N11: =SUM(E11:M11) -> 20 | O11: 2 | P11: 2 | Q11: 2 | R11: 2 | S11: 1.87 | T11: 2.88 | U11: 0 | V11: 2 | W11: =SUM(O11:V11) -> 14.75 | X11: 4.5 | Y11: 5.83 | Z11: 0 | AA11: 2.56 | AB11: 1 | AC11: 0 | AD11: 0 | AE11: 0 | AF11: 2 | AG11: =SUM(X11:AF11) -> 15.89 | AH11: =N11+W11+AG11 -> 50.64 | AI11: 5 | AJ11: 5 | AK11: 5 | AL11: 5 | AM11: 5 | AN11: 10 | AO11: 8.6 | AP11: 10 | AQ11: 10 | AR11: 0.5 | AS11: 2 | AT11: 3 | AU11: 2 | AV11: =SUM(AI11:AU11) -> 71.1 | AW11: 75 | AX11: =D11+AH11+AV11+AW11 -> 266.74 | AY11: =(10%*D11)+(50%*AH11)+(30%*AV11)+(10%*AW11) -> 61.15
A12: 4 | D12: =32*2 -> 64 | E12: 3 | F12: 2 | G12: 2 | H12: 4 | I12: 4 | J12: 2.1 | K12: 2 | L12: 1.5 | M12: 5 | N12: =SUM(E12:M12) -> 25.6 | O12: 2 | P12: 2 | Q12: 2 | R12: 2 | S12: 1.56 | T12: 4.64 | U12: 1.5 | V12: 2 | W12: =SUM(O12:V12) -> 17.7 | X12: 4.5 | Y12: 6.3 | Z12: 2.875 | AA12: 3.5 | AB12: 1 | AC12: 1.2 | AD12: 4 | AE12: 4.27 | AF12: 2 | AG12: =SUM(X12:AF12) -> 29.645 | AH12: =N12+W12+AG12 -> 72.945 | AI12: 5 | AJ12: 5 | AK12: 5 | AL12: 5 | AM12: 5 | AN12: 10 | AO12: 8.17 | AP12: 10 | AQ12: 10 | AR12: 5 | AS12: 7.7879252 | AT12: 5 | AU12: 2 | AV12: =SUM(AI12:AU12) -> 82.957925 | AW12: 85 | AX12: =D12+AH12+AV12+AW12 -> 304.90293 | AY12: =(10%*D12)+(50%*AH12)+(30%*AV12)+(10%*AW12) -> 76.259878
A13: 5 | D13: =27*2 -> 54 | E13: 2 | F13: 1 | G13: 0.5 | H13: 1 | I13: 0.5 | J13: 2 | K13: 1.2 | L13: 1 | M13: 5 | N13: =SUM(E13:M13) -> 14.2 | O13: 2 | P13: 2 | Q13: 2 | R13: 2 | S13: 1.87 | T13: 2.88 | U13: 0 | V13: 2 | W13: =SUM(O13:V13) -> 14.75 | X13: 3.5 | Y13: 4.86 | Z13: 1 | AA13: 3.17 | AB13: 1 | AC13: 0 | AD13: 0.83 | AE13: 2.8 | AF13: 3 | AG13: =SUM(X13:AF13) -> 20.16 | AH13: =N13+W13+AG13 -> 49.11 | AI13: 5 | AJ13: 5 | AK13: 5 | AL13: 5 | AM13: 5 | AN13: 9.185 | AO13: 3.44 | AP13: 10 | AQ13: 10 | AR13: 3 | AS13: 5.5138538 | AT13: 3 | AU13: 2 | AV13: =SUM(AI13:AU13) -> 71.138854 | AW13: 65 | AX13: =D13+AH13+AV13+AW13 -> 239.24885 | AY13: =(10%*D13)+(50%*AH13)+(30%*AV13)+(10%*AW13) -> 57.796656
A14: 6 | D14: =37*2 -> 74 | E14: 2.25 | F14: 1 | G14: 4 | H14: 4 | I14: 3.5 | J14: 2.4 | K14: 1.9 | L14: 1.7 | M14: 5 | N14: =SUM(E14:M14) -> 25.75 | O14: 2 | P14: 2 | Q14: 2 | R14: 2 | S14: 1.65 | T14: 4.72 | U14: 1.2 | V14: 2 | W14: =SUM(O14:V14) -> 17.57 | X14: 3 | Y14: 6.13 | Z14: 4.125 | AA14: 3.17 | AB14: 1 | AC14: 0 | AD14: 3.67 | AE14: 3.66 | AF14: 3 | AG14: =SUM(X14:AF14) -> 27.755 | AH14: =N14+W14+AG14 -> 71.075 | AI14: 5 | AJ14: 5 | AK14: 5 | AL14: 5 | AM14: 5 | AN14: 10 | AO14: 9.46 | AP14: 10 | AQ14: 10 | AR14: 3 | AS14: 8.9031639 | AT14: 5 | AU14: 2 | AV14: =SUM(AI14:AU14) -> 83.363164 | AW14: 75 | AX14: =D14+AH14+AV14+AW14 -> 303.43816 | AY14: =(10%*D14)+(50%*AH14)+(30%*AV14)+(10%*AW14) -> 75.446449
A15: 7 | D15: =35*2 -> 70 | E15: 3 | F15: 1 | G15: 5.5 | H15: 5 | I15: 3.5 | J15: 2.7 | K15: 2 | L15: 1.1 | M15: 5 | N15: =SUM(E15:M15) -> 28.8 | O15: 2 | P15: 2 | Q15: 2 | R15: 2 | S15: 1.87 | T15: 4.72 | U15: 1.92 | V15: 2 | W15: =SUM(O15:V15) -> 18.51 | X15: 4.5 | Y15: 5.93 | Z15: 3.125 | AA15: 3.54 | AB15: 1 | AC15: 1.2 | AD15: 3 | AE15: 4.45 | AF15: 3 | AG15: =SUM(X15:AF15) -> 29.745 | AH15: =N15+W15+AG15 -> 77.055 | AI15: 5 | AJ15: 5 | AK15: 5 | AL15: 5 | AM15: 5 | AN15: 10 | AO15: 8.6 | AP15: 10 | AQ15: 10 | AR15: 6 | AS15: 14.88108 | AT15: 5 | AU15: 5 | AV15: =SUM(AI15:AU15) -> 94.48108 | AW15: 80 | AX15: =D15+AH15+AV15+AW15 -> 321.53608 | AY15: =(10%*D15)+(50%*AH15)+(30%*AV15)+(10%*AW15) -> 81.871824
A16: 8 | D16: =37*2 -> 74 | E16: 3 | F16: 2.25 | G16: 5.5 | H16: 6 | I16: 4 | J16: 2.8 | K16: 1.9 | L16: 1.9 | M16: 5 | N16: =SUM(E16:M16) -> 32.35 | O16: 2 | P16: 2 | Q16: 2 | R16: 2 | S16: 1.78 | T16: 4.32 | U16: 1.56 | V16: 2 | W16: =SUM(O16:V16) -> 17.66 | X16: 4.5 | Y16: 6.13 | Z16: 3.875 | AA16: 3.29 | AB16: 1 | AC16: 1.2 | AD16: 3.83 | AE16: 4.15 | AF16: 3 | AG16: =SUM(X16:AF16) -> 30.975 | AH16: =N16+W16+AG16 -> 80.985 | AI16: 5 | AJ16: 5 | AK16: 5 | AL16: 5 | AM16: 5 | AN16: 9.185 | AO16: 9.89 | AP16: 10 | AQ16: 10 | AR16: 7.5 | AS16: 14.978085 | AT16: 5 | AU16: 5 | AV16: =SUM(AI16:AU16) -> 96.553085 | AW16: 80 | AX16: =D16+AH16+AV16+AW16 -> 331.53808 | AY16: =(10%*D16)+(50%*AH16)+(30%*AV16)+(10%*AW16) -> 84.858425
A17: 9 | D17: =44*2 -> 88 | E17: 3 | F17: 2 | G17: 6.5 | H17: 7 | I17: 4 | J17: 2.45 | K17: 1.9 | L17: 1.8 | M17: 5 | N17: =SUM(E17:M17) -> 33.65 | O17: 2 | P17: 1.54 | Q17: 2 | R17: 1.82 | S17: 1.93 | T17: 4.8 | U17: 1.3 | V17: 2 | W17: =SUM(O17:V17) -> 17.39 | X17: 5 | Y17: 6.42 | Z17: 4.63 | AA17: 3.59 | AB17: 1 | AC17: 0 | AD17: 4.3 | AE17: 4.76 | AF17: 2.75 | AG17: =SUM(X17:AF17) -> 32.45 | AH17: =N17+W17+AG17 -> 83.49 | AI17: 5 | AJ17: 5 | AK17: 5 | AL17: 5 | AM17: 5 | AN17: 10 | AO17: 9.89 | AP17: 10 | AQ17: 10 | AR17: 7 | AS17: 14.977696 | AT17: 3 | AU17: 5 | AV17: =SUM(AI17:AU17) -> 94.867696 | AW17: 90 | AX17: =D17+AH17+AV17+AW17 -> 356.3577 | AY17: =(10%*D17)+(50%*AH17)+(30%*AV17)+(10%*AW17) -> 88.005309
A18: 10 | D18: =37*2 -> 74 | E18: 3 | F18: 1 | G18: 5 | H18: 4 | I18: 4 | J18: 2.1 | K18: 1.8 | L18: 1.4 | M18: 5 | N18: =SUM(E18:M18) -> 27.3 | O18: 2 | P18: 2 | Q18: 2 | R18: 1.87 | S18: 1.87 | T18: 5.12 | U18: 1.5 | V18: 2 | W18: =SUM(O18:V18) -> 18.36 | X18: 4.5 | Y18: 6.03 | Z18: 3.63 | AA18: 3.29 | AB18: 1 | AC18: 1 | AD18: 3.67 | AE18: 4.51 | AF18: 3 | AG18: =SUM(X18:AF18) -> 30.63 | AH18: =N18+W18+AG18 -> 76.29 | AI18: 5 | AJ18: 5 | AK18: 5 | AL18: 5 | AM18: 5 | AN18: 10 | AO18: 9.89 | AP18: 10 | AQ18: 10 | AR18: 6 | AS18: 14.948692 | AT18: 3 | AU18: 5 | AV18: =SUM(AI18:AU18) -> 93.838692 | AW18: 70 | AX18: =D18+AH18+AV18+AW18 -> 314.12869 | AY18: =(10%*D18)+(50%*AH18)+(30%*AV18)+(10%*AW18) -> 80.696608
A19: 11 | D19: =40*2 -> 80 | E19: 3 | F19: 0 | G19: 5.5 | H19: 4 | I19: 3 | J19: 2.5 | K19: 0.25 | L19: 0.25 | M19: 5 | N19: =SUM(E19:M19) -> 23.5 | O19: 2 | P19: 2 | Q19: 2 | R19: 2 | S19: 1.87 | T19: 5.04 | U19: 0 | V19: 2 | W19: =SUM(O19:V19) -> 16.91 | X19: 4 | Y19: 6.22 | Z19: 3.5 | AA19: 2.8 | AB19: 1 | AC19: 0.2 | AD19: 3.67 | AE19: 4.15 | AF19: 3 | AG19: =SUM(X19:AF19) -> 28.54 | AH19: =N19+W19+AG19 -> 68.95 | AI19: 5 | AJ19: 5 | AK19: 5 | AL19: 5 | AM19: 5 | AN19: 10 | AO19: 5.16 | AP19: 10 | AQ19: 10 | AR19: 4 | AS19: 3.0394183 | AT19: 5 | AU19: 2 | AV19: =SUM(AI19:AU19) -> 74.199418 | AW19: 85 | AX19: =D19+AH19+AV19+AW19 -> 308.14942 | AY19: =(10%*D19)+(50%*AH19)+(30%*AV19)+(10%*AW19) -> 73.234825
A20: 12 | D20: =38*2 -> 76 | E20: 3 | F20: 1 | G20: 6 | H20: 6 | I20: 3.5 | J20: 2.75 | K20: 1.9 | L20: 1.2 | M20: 5 | N20: =SUM(E20:M20) -> 30.35 | O20: 2 | P20: 2 | Q20: 2 | R20: 2 | S20: 1.87 | T20: 6 | U20: 1.5 | V20: 2 | W20: =SUM(O20:V20) -> 19.37 | X20: 5 | Y20: 6.32 | Z20: 3.875 | AA20: 3.54 | AB20: 1 | AC20: 1.5 | AD20: 3.83 | AE20: 3.66 | AF20: 3 | AG20: =SUM(X20:AF20) -> 31.725 | AH20: =N20+W20+AG20 -> 81.445 | AI20: 5 | AJ20: 5 | AK20: 5 | AL20: 5 | AM20: 5 | AN20: 10 | AO20: 9.89 | AP20: 10 | AQ20: 10 | AR20: 7 | AS20: 15.041887 | AT20: 3 | AU20: 5 | AV20: =SUM(AI20:AU20) -> 94.931887 | AW20: 95 | AX20: =D20+AH20+AV20+AW20 -> 347.37689 | AY20: =(10%*D20)+(50%*AH20)+(30%*AV20)+(10%*AW20) -> 86.302066
A21: 13 | D21: =41*2 -> 82 | E21: 3 | F21: 2 | G21: 6.5 | H21: 6 | I21: 2.5 | J21: 2.7 | K21: 1.5 | L21: 1.5 | M21: 5 | N21: =SUM(E21:M21) -> 30.7 | O21: 2 | P21: 2 | Q21: 2 | R21: 2 | S21: 1.76 | T21: 5.12 | U21: 0.1 | V21: 2 | W21: =SUM(O21:V21) -> 16.98 | X21: 5 | Y21: 6.61 | Z21: 3.875 | AA21: 3.78 | AB21: 1 | AC21: 1 | AD21: 4 | AE21: 1.5 | AF21: 3 | AG21: =SUM(X21:AF21) -> 29.765 | AH21: =N21+W21+AG21 -> 77.445 | AI21: 5 | AJ21: 5 | AK21: 5 | AL21: 5 | AM21: 5 | AN21: 10 | AO21: 9.89 | AP21: 10 | AQ21: 10 | AR21: 4 | AS21: 15.013531 | AT21: 3 | AU21: 5 | AV21: =SUM(AI21:AU21) -> 91.903531 | AW21: 75 | AX21: =D21+AH21+AV21+AW21 -> 326.34853 | AY21: =(10%*D21)+(50%*AH21)+(30%*AV21)+(10%*AW21) -> 81.993559
A22: 14 | D22: =33*2 -> 66 | E22: 2 | F22: 2 | G22: 4.5 | H22: 3 | I22: 2.5 | J22: 2.3 | K22: 1.7 | L22: 1.8 | M22: 5 | N22: =SUM(E22:M22) -> 24.8 | O22: 2 | P22: 2 | Q22: 2 | R22: 2 | S22: 1.98 | T22: 5.36 | U22: 0.8 | V22: 2 | W22: =SUM(O22:V22) -> 18.14 | X22: 4.5 | Y22: 6.03 | Z22: 3.625 | AA22: 3.17 | AB22: 1 | AC22: 1.2 | AD22: 4.33 | AE22: 4.39 | AF22: 3 | AG22: =SUM(X22:AF22) -> 31.245 | AH22: =N22+W22+AG22 -> 74.185 | AI22: 5 | AJ22: 5 | AK22: 5 | AL22: 5 | AM22: 5 | AN22: 10 | AO22: 4.73 | AP22: 10 | AQ22: 10 | AR22: 5 | AS22: 2 | AT22: 3 | AU22: 2 | AV22: =SUM(AI22:AU22) -> 71.73 | AW22: 75 | AX22: =D22+AH22+AV22+AW22 -> 286.915 | AY22: =(10%*D22)+(50%*AH22)+(30%*AV22)+(10%*AW22) -> 72.7115
A23: 15 | D23: =28*2 -> 56 | E23: 2 | F23: 1 | G23: 3 | H23: 1 | I23: 2 | J23: 2 | K23: 1.7 | L23: 1.3 | M23: 5 | N23: =SUM(E23:M23) -> 19 | O23: 2 | P23: 2 | Q23: 2 | R23: 2 | S23: 1.87 | T23: 3.92 | U23: 1.11 | V23: 2 | W23: =SUM(O23:V23) -> 16.9 | X23: 4.5 | Y23: 5.93 | Z23: 1.875 | AA23: 2.8 | AB23: 0.5 | AC23: 0 | AD23: 1.5 | AE23: 2.44 | AF23: 2.75 | AG23: =SUM(X23:AF23) -> 22.295 | AH23: =N23+W23+AG23 -> 58.195 | AI23: 5 | AJ23: 5 | AK23: 5 | AL23: 5 | AM23: 5 | AN23: 10 | AO23: 9.89 | AP23: 10 | AQ23: 10 | AR23: 7 | AS23: 4.5444493 | AT23: 5 | AU23: 2 | AV23: =SUM(AI23:AU23) -> 83.434449 | AW23: 65 | AX23: =D23+AH23+AV23+AW23 -> 262.62945 | AY23: =(10%*D23)+(50%*AH23)+(30%*AV23)+(10%*AW23) -> 66.227835

Sheet URUT-SIKLUS1
A1: REKAPITULASI NILAI LOMBA KETERAMPILAN SISWA (LKS) KABUPATEN DEMAK
A2: MATA LOMBA AKUNTANSI
A3: DEMAK, 13 SEPTEMBER 2017
N4: 50 | X4: 50
A5: No. Peserta | B5: Nama Peserta | C5: Nama Sekolah | D5: Skor Teori Akuntansi | E5: Skor Praktik Akuntansi Manual SESI 1 | O5: Skor Praktek Akuntansi Manual SESI 3 | Z5: Skor Aplikasi Komputer Akuntansi | AP5: Skor Presentasi | AW5: TOTAL1 | AX5: TOTAL2 | AY5: Nilai Akhir Total | AZ5: Nilai Akhir Total Konversi
E6: Jurnal Pembelian | F6: Jurnal Penjualan | G6: Pengeluaran kas | H6: Penerimaan Kas | I6: Jurnal Umum | J6: Kartu Persediaan | K6: BBP Piutang | L6: BBP Utang | M6: Sikap | N6: entri jurnal | O6: Penyesuaian | P6: Kertas kerja | Q6: Neraca | R6: Laba Rugi | S6: Laba Ditahan | T6: Arus Kas | U6: jurnal penutup | V6: NS penutupan | W6: sikap | X6: laporan keuangan | Y6: Sub Total | Z6: data bisnis | AA6: daftar akun | AB6: data pelanggan | AC6: data supplier | AD6: persediaan | AE6: J. Kas Masuk | AF6: J. Kas Keluar | AG6: J. Pemb | AH6: J. Penj | AI6: J. Umum | AJ6: J. Penyesuaian | AK6: L/R | AL6: LAK | AM6: Neraca | AN6: Sikap | AO6: Sub Total | AP6: penguasaan materi | AQ6: sistematika penyajian | AR6: kebenaran menjawab | AS6: penampilan | AT6: bahasa inggris | AU6: penggunaan media | AV6: Sub Total
D7: 0.1 | N7: 0.5 | X7: 0.5 | Y7: =(N7+X7)/2 -> 0.5 | AO7: 0.35 | AP7: 30 | AQ7: 10 | AR7: 30 | AS7: 10 | AT7: 15 | AU7: 5 | AV7: 0.1 | AY7: =D7+Y7+AO7 -> 0.95 | AZ7: 1
D8: 100 | E8: 4 | F8: 4 | G8: 10 | H8: 11 | I8: 5 | J8: 6 | K8: 3 | L8: 2 | M8: 5 | N8: 45 | O8: 9 | P8: 10 | Q8: 6 | R8: 6 | S8: 3 | T8: 3 | U8: 5 | V8: 5 | W8: 3 | X8: =SUM(O8:W8) -> 50 | Y8: =N8+X8 -> 95 | Z8: 5 | AA8: 5 | AB8: 5 | AC8: 5 | AD8: 5 | AE8: 10 | AF8: 10 | AG8: 10 | AH8: 10 | AI8: 7 | AJ8: 8 | AK8: 5 | AL8: 5 | AM8: 5 | AN8: 5 | AO8: =SUM(Z8:AN8) -> 100 | AP8: 30 | AQ8: 10 | AR8: 30 | AS8: 10 | AT8: 15 | AU8: 5 | AV8: =SUM(AP8:AU8) -> 100 | AY8: =AO8+Y8+D8 -> 295 | AZ8: =(20%*D8)+(50%*Y8)+(30%*AO8) -> 97.5
A9: 1 | N9: =SUM(E9:M9) -> 0 | X9: =SUM(O9:W9) -> 0 | Y9: =N9+X9 -> 0 | AN9: 5 | AO9: =SUM(Z9:AN9) -> 5 | AY9: =AO9+Y9+D9 -> 5 | AZ9: =(20%*D9)+(50%*Y9)+(30%*AO9) -> 1.5
A10: 2 | N10: =SUM(E10:M10) -> 0 | X10: =SUM(O10:W10) -> 0 | Y10: =N10+X10 -> 0 | AN10: 5 | AO10: =SUM(Z10:AN10) -> 5 | AV10: =SUM(AP10:AU10) -> 0 | AW10: =(10%*E10)+(50%*Y10)+(30%*AO10)+(10%*AV10) -> 1.5 | AX10: =E10+Y10+AO10+AV10 -> 5 | AY10: =AO10+Y10+D10 -> 5 | AZ10: =(20%*D10)+(50%*Y10)+(30%*AO10) -> 1.5
A11: 3 | N11: =SUM(E11:M11) -> 0 | X11: =SUM(O11:W11) -> 0 | Y11: =N11+X11 -> 0 | AN11: 5 | AO11: =SUM(Z11:AN11) -> 5 | AV11: =SUM(AP11:AU11) -> 0 | AW11: =(10%*E11)+(50%*Y11)+(30%*AO11)+(10%*AV11) -> 1.5 | AX11: =E11+Y11+AO11+AV11 -> 5 | AY11: =AO11+Y11+D11 -> 5 | AZ11: =(20%*D11)+(50%*Y11)+(30%*AO11) -> 1.5
A12: 4 | N12: =SUM(E12:M12) -> 0 | X12: =SUM(O12:W12) -> 0 | Y12: =N12+X12 -> 0 | AN12: 5 | AO12: =SUM(Z12:AN12) -> 5 | AV12: =SUM(AP12:AU12) -> 0 | AW12: =(10%*E12)+(50%*Y12)+(30%*AO12)+(10%*AV12) -> 1.5 | AX12: =E12+Y12+AO12+AV12 -> 5 | AY12: =AO12+Y12+D12 -> 5 | AZ12: =(20%*D12)+(50%*Y12)+(30%*AO12) -> 1.5
A13: 5 | N13: =SUM(E13:M13) -> 0 | X13: =SUM(O13:W13) -> 0 | Y13: =N13+X13 -> 0 | AN13: 5 | AO13: =SUM(Z13:AN13) -> 5 | AV13: =SUM(AP13:AU13) -> 0 | AW13: =(10%*E13)+(50%*Y13)+(30%*AO13)+(10%*AV13) -> 1.5 | AX13: =E13+Y13+AO13+AV13 -> 5 | AY13: =AO13+Y13+D13 -> 5 | AZ13: =(20%*D13)+(50%*Y13)+(30%*AO13) -> 1.5
A14: 6 | N14: =SUM(E14:M14) -> 0 | X14: =SUM(O14:W14) -> 0 | Y14: =N14+X14 -> 0 | AN14: 5 | AO14: =SUM(Z14:AN14) -> 5 | AY14: =AO14+Y14+D14 -> 5 | AZ14: =(20%*D14)+(50%*Y14)+(30%*AO14) -> 1.5
A15: 7 | N15: =SUM(E15:M15) -> 0 | X15: =SUM(O15:W15) -> 0 | Y15: =N15+X15 -> 0 | AN15: 5 | AO15: =SUM(Z15:AN15) -> 5 | AY15: =AO15+Y15+D15 -> 5 | AZ15: =(20%*D15)+(50%*Y15)+(30%*AO15) -> 1.5
A16: 8 | N16: =SUM(E16:M16) -> 0 | X16: =SUM(O16:W16) -> 0 | Y16: =N16+X16 -> 0 | AN16: 5 | AO16: =SUM(Z16:AN16) -> 5 | AV16: =SUM(AP16:AU16) -> 0 | AW16: =(10%*E16)+(50%*Y16)+(30%*AO16)+(10%*AV16) -> 1.5 | AX16: =E16+Y16+AO16+AV16 -> 5 | AY16: =AO16+Y16+D16 -> 5 | AZ16: =(20%*D16)+(50%*Y16)+(30%*AO16) -> 1.5
A17: 9 | N17: =SUM(E17:M17) -> 0 | X17: =SUM(O17:W17) -> 0 | Y17: =N17+X17 -> 0 | AN17: 5 | AO17: =SUM(Z17:AN17) -> 5 | AY17: =AO17+Y17+D17 -> 5 | AZ17: =(20%*D17)+(50%*Y17)+(30%*AO17) -> 1.5
A18: 10 | N18: =SUM(E18:M18) -> 0 | X18: =SUM(O18:W18) -> 0 | Y18: =N18+X18 -> 0 | AN18: 5 | AO18: =SUM(Z18:AN18) -> 5 | AY18: =AO18+Y18+D18 -> 5 | AZ18: =(20%*D18)+(50%*Y18)+(30%*AO18) -> 1.5
A19: 11 | N19: =SUM(E19:M19) -> 0 | X19: =SUM(O19:W19) -> 0 | Y19: =N19+X19 -> 0 | AN19: 5 | AO19: =SUM(Z19:AN19) -> 5 | AY19: =AO19+Y19+D19 -> 5 | AZ19: =(20%*D19)+(50%*Y19)+(30%*AO19) -> 1.5
A20: 12 | N20: =SUM(E20:M20) -> 0 | X20: =SUM(O20:W20) -> 0 | Y20: =N20+X20 -> 0 | AN20: 5 | AO20: =SUM(Z20:AN20) -> 5 | AY20: =AO20+Y20+D20 -> 5 | AZ20: =(20%*D20)+(50%*Y20)+(30%*AO20) -> 1.5
A21: 13 | N21: =SUM(E21:M21) -> 0 | X21: =SUM(O21:W21) -> 0 | Y21: =N21+X21 -> 0 | AN21: 5 | AO21: =SUM(Z21:AN21) -> 5 | AY21: =AO21+Y21+D21 -> 5 | AZ21: =(20%*D21)+(50%*Y21)+(30%*AO21) -> 1.5
A22: 14 | N22: =SUM(E22:M22) -> 0 | X22: =SUM(O22:W22) -> 0 | Y22: =N22+X22 -> 0 | AN22: 5 | AO22: =SUM(Z22:AN22) -> 5 | AY22: =AO22+Y22+D22 -> 5 | AZ22: =(20%*D22)+(50%*Y22)+(30%*AO22) -> 1.5
A23: 15 | N23: =SUM(E23:M23) -> 0 | X23: =SUM(O23:W23) -> 0 | Y23: =N23+X23 -> 0 | AN23: 5 | AO23: =SUM(Z23:AN23) -> 5 | AY23: =AO23+Y23+D23 -> 5 | AZ23: =(20%*D23)+(50%*Y23)+(30%*AO23) -> 1.5

Sheet UNDIAN
B1: 1 | D1: 19
D2: 1
B4: 2 | D4: 20
B6: 3 | D6: 21
B8: 4 | D8: 22
B10: 5 | D10: 23
B12: 6 | D12: 24
B14: 7 | D14: 25
B16: 8 | D16: 26
B18: 9 | D18: 27
B20: 10 | D20: 28
B22: 11 | D22: 29
B24: 12 | D24: 30
B26: 13 | D26: 31
... B32: 16 | D32: 34
B34: 17
B36: 18
